featuristic/__init__.py
featuristic/version.py
featuristic/datasets/__init__.py
featuristic/datasets/fetch.py
featuristic/selection/__init__.py
featuristic/selection/genetic_feature_selection.py
featuristic/selection/population.py
featuristic/synthesis/__init__.py
featuristic/synthesis/fitness.py
featuristic/synthesis/genetic_feature_synthesis.py
featuristic/synthesis/mrmr.py
featuristic/synthesis/population.py
featuristic/synthesis/preprocess.py
featuristic/synthesis/program.py
featuristic/synthesis/symbolic_functions.py
featuristic-1.1.0.dist-info/LICENSE.txt
featuristic-1.1.0.dist-info/METADATA
featuristic-1.1.0.dist-info/WHEEL
featuristic-1.1.0.dist-info/top_level.txt
featuristic-1.1.0.dist-info/RECORD
