Metadata-Version: 2.1
Name: featuristic
Version: 1.1.0
Summary: Genetic algorithms for automated feature engineering and feature selection
License: Copyright 2024 Martin Eastwood
Project-URL: homepage, https://www.featuristic.co.uk
Project-URL: repository, https://github.com/martineastwood/featuristic.git
Keywords: data,machine learning,feature engineering,feature selection,model selection,model evaluation,genetic algorithm,optimization,hyperparameter tuning
Classifier: License :: OSI Approved :: MIT License
Classifier: Programming Language :: Python :: 3
Classifier: Programming Language :: Python :: 3.8
Classifier: Programming Language :: Python :: 3.9
Classifier: Programming Language :: Python :: 3.10
Classifier: Programming Language :: Python :: 3.11
Classifier: Programming Language :: Python :: 3.12
Classifier: Programming Language :: Python :: 3 :: Only
Requires-Python: >=3.8
License-File: LICENSE.txt
Requires-Dist: matplotlib >=3.0.0
Requires-Dist: numpy >=1.25.0
Requires-Dist: pandas >=2.0.0
Requires-Dist: Pyarrow >=15.0.0
Requires-Dist: scikit-learn >=1.4.0
Requires-Dist: tqdm >=4.32.0
Requires-Dist: ucimlrepo >=0.0.5
Provides-Extra: dev
Requires-Dist: black ; extra == 'dev'
Requires-Dist: build ; extra == 'dev'
Requires-Dist: coverage ; extra == 'dev'
Requires-Dist: coveralls ; extra == 'dev'
Requires-Dist: isort ; extra == 'dev'
Requires-Dist: ipykernel ; extra == 'dev'
Requires-Dist: nbsphinx ; extra == 'dev'
Requires-Dist: pre-commit ; extra == 'dev'
Requires-Dist: pydata-sphinx-theme ; extra == 'dev'
Requires-Dist: pytest ; extra == 'dev'
Requires-Dist: pylint ; extra == 'dev'
Requires-Dist: Sphinx ; extra == 'dev'
